traspider/__init__.py
traspider/commands/__init__.py
traspider/commands/cmdline.py
traspider/commands/create.py
traspider/core/__init__.py
traspider/core/download.py
traspider/core/engine.py
traspider/core/request.py
traspider/core/response.py
traspider/core/scheduler.py
traspider/core/spider.py
traspider/templates/spider_template.tmpl
traspider/util/__init__.py
traspider/util/encrypt.py
traspider/util/exception.py
traspider/util/log.py
traspider/util/traerror.py
traspider/util/element/__init__.py
traspider/util/element/element.py
traspider/util/node_vm/__init__.py
traspider/util/node_vm/node.py
traspider/util/trajson/__init__.py
traspider/util/trajson/ast.py
traspider/util/trajson/lexical.py
traspider/util/trajson/trajson.py
traspider/util/tramysql/__init__.py
traspider/util/tramysql/tramysql.py
traspider-0.1.0.dist-info/LICENSE
traspider-0.1.0.dist-info/METADATA
traspider-0.1.0.dist-info/WHEEL
traspider-0.1.0.dist-info/entry_points.txt
traspider-0.1.0.dist-info/top_level.txt
traspider-0.1.0.dist-info/RECORD
