Metadata-Version: 2.1
Name: traspider
Version: 0.1.0
Summary: An out-of-the-box lightweight asynchronous crawler framework
Author: NTrash
Author-email: yinghui0214@163.com
License: MIT
Classifier: Framework :: AsyncIO
Classifier: Intended Audience :: Developers
Classifier: Development Status :: 3 - Alpha
Classifier: Programming Language :: Python :: 3
Classifier: Operating System :: OS Independent
Requires-Python: >=3.7
License-File: LICENSE
Requires-Dist: aiohttp
Requires-Dist: aiomysql
Requires-Dist: aiosignal
Requires-Dist: aiostream
Requires-Dist: async-timeout
Requires-Dist: asyncio
Requires-Dist: attrs
Requires-Dist: chardet
Requires-Dist: charset-normalizer
Requires-Dist: colorama
Requires-Dist: frozenlist
Requires-Dist: idna
Requires-Dist: loguru
Requires-Dist: lxml
Requires-Dist: multidict
Requires-Dist: node-vm2 (==0.3.5)
Requires-Dist: PyMySQL
Requires-Dist: win32-setctime
Requires-Dist: yarl
